Metadata-Version: 2.1
Name: signalstickers-client-fork-laggykiller
Version: 3.3.0.post2
Summary: A client for the Signal stickers API
Home-page: https://github.com/laggykiller/signalstickers-client
Author: Romain Ricard
Author-email: contact+stickerclient@romainricard.fr
Classifier: Programming Language :: Python :: 3
Classifier: License :: OSI Approved :: GNU Lesser General Public License v3 (LGPLv3)
Classifier: Operating System :: OS Independent
Classifier: Topic :: Communications :: Chat
Requires-Python: >=3.6
License-File: LICENSE
Requires-Dist: anyio >=3.0.0
Requires-Dist: httpx >=0.16.1
Requires-Dist: cryptography >=3.1.1
Requires-Dist: protobuf >=3.13.0
